mcpi_command_utils/__init__.py
mcpi_command_utils/client.py
mcpi_command_utils/server.py
mcpi_command_utils-1.0.dist-info/LICENSE
mcpi_command_utils-1.0.dist-info/METADATA
mcpi_command_utils-1.0.dist-info/WHEEL
mcpi_command_utils-1.0.dist-info/top_level.txt
mcpi_command_utils-1.0.dist-info/RECORD
