Metadata-Version: 2.1
Name: mcpi-command-utils
Version: 1.0
Summary: A minimal server and client for the Minecraft Pi API.
Home-page: UNKNOWN
Author: The StevePi Organization
Maintainer: LEHAtupointow
Maintainer-email: leha2@tuxfamily.org
License: UNKNOWN
Platform: UNKNOWN
